simplefilesettings/__init__.py
simplefilesettings/_base.py
simplefilesettings/json.py
simplefilesettings/json5.py
simplefilesettings/serializer.py
simplefilesettings/toml.py
simplefilesettings/yaml.py
simple_file_settings-0.1.7.dist-info/WHEEL
simple_file_settings-0.1.7.dist-info/METADATA
simple_file_settings-0.1.7.dist-info/RECORD
