Metadata-Version: 2.3
Name: simple-file-settings
Version: 0.1.7
Summary: Easily load and save simple configuration data to and from disk through a type-checked data class.
Author: Nathan Vaughn
Author-email: Nathan Vaughn <nath@nvaughn.email>
Classifier: License :: OSI Approved :: MIT License
Classifier: Intended Audience :: Developers
Classifier: Topic :: Software Development :: Libraries :: Python Modules
Classifier: Programming Language :: Python :: 3.9
Classifier: Programming Language :: Python :: 3.10
Classifier: Programming Language :: Python :: 3.11
Classifier: Programming Language :: Python :: 3.12
Classifier: Programming Language :: Python :: 3.13
Classifier: Programming Language :: Python :: 3.14
Requires-Dist: typeguard>=4.2.1
Requires-Dist: pyjson5>=1.6.6 ; extra == 'json5'
Requires-Dist: tomli>=2.0.1 ; python_full_version < '3.11' and extra == 'toml'
Requires-Dist: tomli-w>=1.0.0 ; extra == 'toml'
Requires-Dist: pyyaml>=6.0.1 ; extra == 'yaml'
Requires-Python: >=3.9
Project-URL: Homepage, https://github.com/NathanVaughn/simple-file-settings
Project-URL: Issues, https://github.com/NathanVaughn/simple-file-settings/issues
Project-URL: Repository, https://github.com/NathanVaughn/simple-file-settings.git
Provides-Extra: json5
Provides-Extra: toml
Provides-Extra: yaml
